pyarcher/__init__.py
pyarcher/application.py
pyarcher/archer.py
pyarcher/archer_types.py
pyarcher/base.py
pyarcher/exceptions.py
pyarcher/field.py
pyarcher/field_type_enum.py
pyarcher/group.py
pyarcher/record.py
pyarcher/stubber.py
pyarcher/user.py
pyarcher/values_list.py
pyarcher-0.6.1.dist-info/AUTHORS.rst
pyarcher-0.6.1.dist-info/LICENSE
pyarcher-0.6.1.dist-info/METADATA
pyarcher-0.6.1.dist-info/WHEEL
pyarcher-0.6.1.dist-info/top_level.txt
pyarcher-0.6.1.dist-info/RECORD
