Metadata-Version: 2.1
Name: pyarcher
Version: 0.6.1
Summary: Python client library for interfacing with RSA Archer.
Home-page: https://github.com/kylecribbs/pyarcher
Author: Kyle Cribbs
Author-email: kylecribbs@outlook.com
License: MIT license
Keywords: pyarcher
Platform: UNKNOWN
Classifier: Development Status :: 2 - Pre-Alpha
Classifier: Intended Audience :: Developers
Classifier: License :: OSI Approved :: MIT License
Classifier: Natural Language :: English
Classifier: Programming Language :: Python :: 3.7
Requires-Dist: requests (>=2.22.0)
Requires-Dist: requests-mock (==1.7.0)
Provides-Extra: db
Requires-Dist: SQLAlchemy (>=1.3.13) ; extra == 'db'
Requires-Dist: pyodbc (>=4.0.28) ; extra == 'db'
Requires-Dist: xmltodict (==0.12.0) ; extra == 'db'
